neuralbandit/__init__.py
neuralbandit/algorithm.py
neuralbandit/data.py
neuralbandit/game.py
neuralbandit/sota.py
neuralbandit-0.1.2.dist-info/WHEEL
neuralbandit-0.1.2.dist-info/METADATA
neuralbandit-0.1.2.dist-info/RECORD
